stand/__init__.py
stand/_base.py
stand/_proxies.py
stand/config.py
stand/crawler.py
stand/db.py
stand/main.py
stand/middlewares.py
stand/utils.py
stand/validator.py
stand-0.1.11.dist-info/entry_points.txt
stand-0.1.11.dist-info/LICENSE
stand-0.1.11.dist-info/WHEEL
stand-0.1.11.dist-info/METADATA
stand-0.1.11.dist-info/RECORD
