Metadata-Version: 2.1
Name: stand
Version: 0.1.11
Summary: IP代理池
Home-page: https://github.com/lin-zone/stand
License: MIT
Author: lin-zone
Author-email: z_one10@163.com
Requires-Python: >=3.6,<4.0
Classifier: License :: OSI Approved :: MIT License
Classifier: Programming Language :: Python :: 3
Classifier: Programming Language :: Python :: 3.6
Classifier: Programming Language :: Python :: 3.7
Requires-Dist: Scrapy (==1.8.0)
Requires-Dist: fake-useragent (==0.1.11)
Requires-Dist: peewee (==3.12.0)
Requires-Dist: schedule (==0.6.0)
